wespeaker_nuaazs/__init__.py
wespeaker_nuaazs/cli/__init__.py
wespeaker_nuaazs/cli/hub.py
wespeaker_nuaazs/cli/speaker.py
wespeaker_nuaazs/cli/utils.py
wespeaker_nuaazs/diar/__init__.py
wespeaker_nuaazs/diar/extract_emb.py
wespeaker_nuaazs/diar/make_fbank.py
wespeaker_nuaazs/diar/make_oracle_sad.py
wespeaker_nuaazs/diar/make_rttm.py
wespeaker_nuaazs/diar/make_system_sad.py
wespeaker_nuaazs/diar/spectral_clusterer.py
wespeaker_nuaazs/models/__init__.py
wespeaker_nuaazs/models/campplus.py
wespeaker_nuaazs/models/convert_repvgg.py
wespeaker_nuaazs/models/ecapa_tdnn.py
wespeaker_nuaazs/models/eres2net.py
wespeaker_nuaazs/models/gemini_dfresnet.py
wespeaker_nuaazs/models/pooling_layers.py
wespeaker_nuaazs/models/projections.py
wespeaker_nuaazs/models/repvgg.py
wespeaker_nuaazs/models/res2net.py
wespeaker_nuaazs/models/resnet.py
wespeaker_nuaazs/models/speaker_model.py
wespeaker_nuaazs/models/tdnn.py
wespeaker_nuaazs/utils/__init__.py
wespeaker_nuaazs/utils/checkpoint.py
wespeaker_nuaazs/utils/dataset_utils_deprecated.py
wespeaker_nuaazs/utils/executor.py
wespeaker_nuaazs/utils/executor_deprecated.py
wespeaker_nuaazs/utils/file_utils.py
wespeaker_nuaazs/utils/schedulers.py
wespeaker_nuaazs/utils/score_metrics.py
wespeaker_nuaazs/utils/utils.py
wespeaker_nuaazs-0.0.5.dist-info/LICENSE
wespeaker_nuaazs-0.0.5.dist-info/METADATA
wespeaker_nuaazs-0.0.5.dist-info/WHEEL
wespeaker_nuaazs-0.0.5.dist-info/entry_points.txt
wespeaker_nuaazs-0.0.5.dist-info/top_level.txt
wespeaker_nuaazs-0.0.5.dist-info/RECORD
