Metadata-Version: 2.1
Name: wespeaker-nuaazs
Version: 0.0.5
Summary: Speaker Embedding
Author: Sheng Zhao
Author-email: zhaosheng@nuaa.edu.cn
License: Apache Software License
Classifier: License :: OSI Approved :: Apache Software License
Classifier: Operating System :: OS Independent
Classifier: Programming Language :: Python :: 3
Requires-Python: >=3.8
License-File: LICENSE
Requires-Dist: tqdm
Requires-Dist: kaldiio
Requires-Dist: torch >=1.12.0
Requires-Dist: torchaudio >=0.12.0
